pykzee/AttachedInfo.py
pykzee/ConfigPlugin.py
pykzee/ManagedTree.py
pykzee/Plugin.py
pykzee/PluginLoaderPlugin.py
pykzee/StateLoggerPlugin.py
pykzee/Tree.py
pykzee/__init__.py
pykzee/__main__.py
pykzee/common.py
pykzee/core/AttachedInfo.py
pykzee/core/CodePlugin.py
pykzee/core/ManagedTree.py
pykzee/core/Plugin.py
pykzee/core/RawStateLoader.py
pykzee/core/StateLoggerPlugin.py
pykzee/core/Tree.py
pykzee/core/__init__.py
pykzee/core/__main__.py
pykzee/core/__version__.py
pykzee/core/common.py
pykzee-0.1.1.dist-info/LICENSE
pykzee-0.1.1.dist-info/METADATA
pykzee-0.1.1.dist-info/WHEEL
pykzee-0.1.1.dist-info/entry_points.txt
pykzee-0.1.1.dist-info/top_level.txt
pykzee-0.1.1.dist-info/RECORD
