Metadata-Version: 2.1
Name: pykzee
Version: 0.1.1
Summary: Core engine allowing plug-ins to operate on a JSON-like state tree
Home-page: https://github.com/spacedentist/pykzee
Author: Sven Over
Author-email: sp@cedenti.st
License: MIT
Download-URL: https://github.com/spacedentist/pykzee/archive/0.1.1.tar.gz
Platform: UNKNOWN
Requires-Dist: aiofiles (>=0.4.0)
Requires-Dist: watchdog (>=0.9.0)
Requires-Dist: pyimmutable (>=0.2.0)
